picketer/__init__.py
picketer/api_client.py
picketer/configuration.py
picketer/rest.py
picketer/apis/__init__.py
picketer/apis/attractions_api.py
picketer/apis/classifications_api.py
picketer/apis/events_api.py
picketer/apis/venues_api.py
picketer/models/__init__.py
picketer/models/access.py
picketer/models/address.py
picketer/models/area.py
picketer/models/attraction.py
picketer/models/box_office_info.py
picketer/models/chronology.py
picketer/models/city.py
picketer/models/classification.py
picketer/models/classification_type.py
picketer/models/container.py
picketer/models/country.py
picketer/models/dates.py
picketer/models/dma.py
picketer/models/duration.py
picketer/models/embedded.py
picketer/models/end_time.py
picketer/models/event.py
picketer/models/event_images.py
picketer/models/field.py
picketer/models/field_type.py
picketer/models/general_info.py
picketer/models/genre.py
picketer/models/genre_details.py
picketer/models/image.py
picketer/models/link.py
picketer/models/links.py
picketer/models/location.py
picketer/models/market.py
picketer/models/page.py
picketer/models/place.py
picketer/models/presale_date.py
picketer/models/price.py
picketer/models/promoter.py
picketer/models/public_date.py
picketer/models/sales.py
picketer/models/seat_map.py
picketer/models/segment.py
picketer/models/segment_details.py
picketer/models/social.py
picketer/models/state.py
picketer/models/status.py
picketer/models/sub_genre.py
picketer/models/sub_genre_details.py
picketer/models/time.py
picketer/models/time_value.py
picketer/models/twitter.py
picketer/models/type.py
picketer/models/venue.py
picketer/models/zone.py
picketer-1.0.0.dist-info/DESCRIPTION.rst
picketer-1.0.0.dist-info/METADATA
picketer-1.0.0.dist-info/RECORD
picketer-1.0.0.dist-info/WHEEL
picketer-1.0.0.dist-info/metadata.json
picketer-1.0.0.dist-info/top_level.txt
test/__init__.py
test/test_access.py
test/test_address.py
test/test_area.py
test/test_attraction.py
test/test_attractions_api.py
test/test_box_office_info.py
test/test_chronology.py
test/test_city.py
test/test_classification.py
test/test_classification_type.py
test/test_classifications_api.py
