Metadata-Version: 1.0
Name: picketer
Version: 1.0.0
Summary: Ticketmaster Discovery API client
Home-page: https://github.com/arcward/picketer
Author: Edward Wells
Author-email: git@edward.sh
License: MIT
Keywords: Swagger,Ticketmaster Discovery API
Platform: UNKNOWN
